WEEK1/Day-2/verilog_files/dff_syncres.v
module dff_syncres (input clk, input sync_reset, input d, output reg q);
    always @ (posedge clk)
    begin
        if(sync_reset)
            q <= 1'b0;
        else    
            q <= d;
    end
endmodule

WEEK1/Day-2/verilog_files/tb_dff_syncres.v
`timescale 1ns / 1ps
module tb_dff_syncres;
    reg clk, sync_reset, d;
    wire q;
    
    dff_syncres uut(.clk(clk),.sync_reset(sync_reset),.d(d),.q(q));
    
    initial begin
        $dumpfile("tb_dff_syncres.vcd");
        $dumpvars(0,tb_dff_syncres);
        clk = 0; sync_reset = 1; d = 0;
        #3000 $finish;
    end
    
    always #10 clk = ~clk;
    always #23 d = ~d;
    always #547 sync_reset = ~sync_reset;
endmodule

WEEK1/Day-2/verilog_files/tb_dff_syncres.vcd
$date
	Sat Sep 27 22:55:55 2025
$end
$version
	Icarus Verilog
$end
$timescale
	1ps
$end
$scope module tb_dff_syncres $end
$var wire 1 ! q $end
$var reg 1 " clk $end
$var reg 1 # d $end
$var reg 1 $ sync_reset $end
$scope module uut $end
$var wire 1 " clk $end
$var wire 1 # d $end
$var wire 1 $ sync_reset $end
$var reg 1 ! q $end
$upscope $end
$upscope $end
$enddefinitions $end
$comment Show the parameter values. $end
$dumpall
$end
#0
$dumpvars
1$
0#
0"
x!
$end
#10000
0!
1"
#20000
0"
#23000
1#
#30000
1"
#40000
0"
#46000
0#
#50000
1"
#60000
0"
#69000
1#
#70000
1"
#80000
0"
#90000
1"
#92000
0#
#100000
0"
#110000
1"
#115000
1#
#120000
0"
#130000
1"
#138000
0#
#140000
0"
#150000
1"
#160000
0"
#161000
1#
#170000
1"
#180000
0"
#184000
0#
#190000
1"
#200000
0"
#207000
1#
#210000
1"
#220000
0"
#230000
1"
0#
#240000
0"
#250000
1"
#253000
1#
#260000
0"
#270000
1"
#276000
0#
#280000
0"
#290000
1"
#299000
1#
#300000
0"
#310000
1"
#320000
0"
#322000
0#
#330000
1"
#340000
0"
#345000
1#
#350000
1"
#360000
0"
#368000
0#
#370000
1"
#380000
0"
#390000
1"
#391000
1#
#400000
0"
#410000
1"
#414000
0#
#420000
0"
#430000
1"
#437000
1#
#440000
0"
#450000
1"
#460000
0"
0#
#470000
1"
#480000
0"
#483000
1#
#490000
1"
#500000
0"
#506000
0#
#510000
1"
#520000
0"
#529000
1#
#530000
1"
#540000
0"
#547000
0$
#550000
1!
1"
#552000
0#
#560000
0"
#570000
0!
1"
#575000
1#
#580000
0"
#590000
1!
1"
#598000
0#
#600000
0"
#610000
0!
1"
#620000
0"
#621000
1#
#630000
1!
1"
#640000
0"
#644000
0#
#650000
0!
1"
#660000
0"
#667000
1#
#670000
1!
1"
#680000
0"
#690000
0!
1"
0#
#700000
0"
#710000
1"
#713000
1#
#720000
0"
#730000
1!
1"
#736000
0#
#740000
0"
#750000
0!
1"
#759000
1#
#760000
0"
#770000
1!
1"
#780000
0"
#782000
0#
#790000
0!
1"
#800000
0"
#805000
1#
#810000
1!
1"
#820000
0"
#828000
0#
#830000
0!
1"
#840000
0"
#850000
1"
#851000
1#
#860000
0"
#870000
1!
1"
#874000
0#
#880000
0"
#890000
0!
1"
#897000
1#
#900000
0"
#910000
1!
1"
#920000
0"
0#
#930000
0!
1"
#940000
0"
#943000
1#
#950000
1!
1"
#960000
0"
#966000
0#
#970000
0!
1"
#980000
0"
#989000
1#
#990000
1!
1"
#1000000
0"
#1010000
1"
#1012000
0#
#1020000
0"
#1030000
0!
1"
#1035000
1#
#1040000
0"
#1050000
1!
1"
#1058000
0#
#1060000
0"
#1070000
0!
1"
#1080000
0"
#1081000
1#
#1090000
1!
1"
#1094000
1$
#1100000
0"
#1104000
0#
#1110000
0!
1"
#1120000
0"
#1127000
1#
#1130000
1"
#1140000
0"
#1150000
1"
0#
#1160000
0"
#1170000
1"
#1173000
1#
#1180000
0"
#1190000
1"
#1196000
0#
#1200000
0"
#1210000
1"
#1219000
1#
#1220000
0"
#1230000
1"
#1240000
0"
#1242000
0#
#1250000
1"
#1260000
0"
#1265000
1#
#1270000
1"
#1280000
0"
#1288000
0#
#1290000
1"
#1300000
0"
#1310000
1"
#1311000
1#
#1320000
0"
#1330000
1"
#1334000
0#
#1340000
0"
#1350000
1"
#1357000
1#
#1360000
0"
#1370000
1"
#1380000
0"
0#
#1390000
1"
#1400000
0"
#1403000
1#
#1410000
1"
#1420000
0"
#1426000
0#
#1430000
1"
#1440000
0"
#1449000
1#
#1450000
1"
#1460000
0"
#1470000
1"
#1472000
0#
#1480000
0"
#1490000
1"
#1495000
1#
#1500000
0"
#1510000
1"
#1518000
0#
#1520000
0"
#1530000
1"
#1540000
0"
#1541000
1#
#1550000
1"
#1560000
0"
#1564000
0#
#1570000
1"
#1580000
0"
#1587000
1#
#1590000
1"
#1600000
0"
#1610000
1"
0#
#1620000
0"
#1630000
1"
#1633000
1#
#1640000
0"
#1641000
0$
#1650000
1!
1"
#1656000
0#
#1660000
0"
#1670000
0!
1"
#1679000
1#
#1680000
0"
#1690000
1!
1"
#1700000
0"
#1702000
0#
#1710000
0!
1"
#1720000
0"
#1725000
1#
#1730000
1!
1"
#1740000
0"
#1748000
0#
#1750000
0!
1"
#1760000
0"
#1770000
1"
#1771000
1#
#1780000
0"
#1790000
1!
1"
#1794000
0#
#1800000
0"
#1810000
0!
1"
#1817000
1#
#1820000
0"
#1830000
1!
1"
#1840000
0"
0#
#1850000
0!
1"
#1860000
0"
#1863000
1#
#1870000
1!
1"
#1880000
0"
#1886000
0#
#1890000
0!
1"
#1900000
0"
#1909000
1#
#1910000
1!
1"
#1920000
0"
#1930000
1"
#1932000
0#
#1940000
0"
#1950000
0!
1"
#1955000
1#
#1960000
0"
#1970000
1!
1"
#1978000
0#
#1980000
0"
#1990000
0!
1"
#2000000
0"
#2001000
1#
#2010000
1!
1"
#2020000
0"
#2024000
0#
#2030000
0!
1"
#2040000
0"
#2047000
1#
#2050000
1!
1"
#2060000
0"
#2070000
0!
1"
0#
#2080000
0"
#2090000
1"
#2093000
1#
#2100000
0"
#2110000
1!
1"
#2116000
0#
#2120000
0"
#2130000
0!
1"
#2139000
1#
#2140000
0"
#2150000
1!
1"
#2160000
0"
#2162000
0#
#2170000
0!
1"
#2180000
0"
#2185000
1#
#2188000
1$
#2190000
1"
#2200000
0"
#2208000
0#
#2210000
1"
#2220000
0"
#2230000
1"
#2231000
1#
#2240000
0"
#2250000
1"
#2254000
0#
#2260000
0"
#2270000
1"
#2277000
1#
#2280000
0"
#2290000
1"
#2300000
0"
0#
#2310000
1"
#2320000
0"
#2323000
1#
#2330000
1"
#2340000
0"
#2346000
0#
#2350000
1"
#2360000
0"
#2369000
1#
#2370000
1"
#2380000
0"
#2390000
1"
#2392000
0#
#2400000
0"
#2410000
1"
#2415000
1#
#2420000
0"
#2430000
1"
#2438000
0#
#2440000
0"
#2450000
1"
#2460000
0"
#2461000
1#
#2470000
1"
#2480000
0"
#2484000
0#
#2490000
1"
#2500000
0"
#2507000
1#
#2510000
1"
#2520000
0"
#2530000
1"
0#
#2540000
0"
#2550000
1"
#2553000
1#
#2560000
0"
#2570000
1"
#2576000
0#
#2580000
0"
#2590000
1"
#2599000
1#
#2600000
0"
#2610000
1"
#2620000
0"
#2622000
0#
#2630000
1"
#2640000
0"
#2645000
1#
#2650000
1"
#2660000
0"
#2668000
0#
#2670000
1"
#2680000
0"
#2690000
1"
#2691000
1#
#2700000
0"
#2710000
1"
#2714000
0#
#2720000
0"
#2730000
1"
#2735000
0$
#2737000
1#
#2740000
0"
#2750000
1!
1"
#2760000
0"
0#
#2770000
0!
1"
#2780000
0"
#2783000
1#
#2790000
1!
1"
#2800000
0"
#2806000
0#
#2810000
0!
1"
#2820000
0"
#2829000
1#
#2830000
1!
1"
#2840000
0"
#2850000
1"
#2852000
0#
#2860000
0"
#2870000
0!
1"
#2875000
1#
#2880000
0"
#2890000
1!
1"
#2898000
0#
#2900000
0"
#2910000
0!
1"
#2920000
0"
#2921000
1#
#2930000
1!
1"
#2940000
0"
#2944000
0#
#2950000
0!
1"
#2960000
0"
#2967000
1#
#2970000
1!
1"
#2980000
0"
#2990000
0!
1"
0#
