WEEK1/Day-4/verilog_files/blocking_caveat.v
module blocking_caveat (input a, input b, input c, output reg d);
    reg x;
    always @ (*)
    begin
        d = x & c;
        x = a | b;
    end
endmodule

WEEK1/Day-4/verilog_files/tb_blocking_caveat.v
`timescale 1ns / 1ps
module tb_blocking_caveat;
    reg a,b,c;
    wire d;

    blocking_caveat uut(.a(a),.b(b),.c(c),.d(d));

    initial begin
        $dumpfile("tb_blocking_caveat.vcd");
        $dumpvars(0,tb_blocking_caveat);
        a=0; b=0; c=0;
        #300 $finish;
    end

    always #75 a = ~a;
    always #10 b = ~b;
    always #55 c = ~c;
endmodule

WEEK1/Day-4/verilog_files/tb_blocking_caveat.vcd
$date
	Sat Sep 27 22:55:55 2025
$end
$version
	Icarus Verilog
$end
$timescale
	1ps
$end
$scope module tb_blocking_caveat $end
$var wire 1 ! d $end
$var reg 1 " a $end
$var reg 1 # b $end
$var reg 1 $ c $end
$scope module uut $end
$var wire 1 " a $end
$var wire 1 # b $end
$var wire 1 $ c $end
$var reg 1 ! d $end
$var reg 1 % x $end
$upscope $end
$upscope $end
$enddefinitions $end
$comment Show the parameter values. $end
$dumpall
$end
#0
$dumpvars
0%
0$
0#
0"
0!
$end
#10000
1%
1#
#20000
0%
0#
#30000
1%
1#
#40000
0%
0#
#50000
1%
1#
#55000
1!
1$
#60000
0%
0#
#70000
1%
0!
1#
#75000
1!
1"
#80000
0#
#90000
1#
#100000
0#
#110000
0!
1#
0$
#120000
0#
#130000
1#
#140000
0#
#150000
1#
0"
#160000
0%
0#
#165000
1$
#170000
1%
1#
#180000
0%
1!
0#
#190000
1%
0!
1#
#200000
0%
1!
0#
#210000
1%
0!
1#
#220000
0%
0#
0$
#225000
1%
1"
#230000
1#
#240000
0#
#250000
1#
#260000
0#
#270000
1#
#275000
1!
1$
#280000
0#
#290000
1#
#300000
0%
0#
0"
