WEEK1/Day-1/verilog_files/multiple_modules.v
module sub_module2 (input a, input b, output y);
    assign y = a | b;
endmodule

module sub_module1 (input a, input b, output y);
    assign y = a & b;
endmodule

module multiple_modules (input a, input b, input c, output y);
    wire net1;
    sub_module1 u1(.a(a),.b(b),.y(net1));
    sub_module2 u2(.a(net1),.b(c),.y(y));
endmodule

WEEK1/Day-1/verilog_files/tb_multiple_modules.v
`timescale 1ns / 1ps
module tb_multiple_modules;
    reg a,b,c;
    wire y;
    
    multiple_modules uut(.a(a),.b(b),.c(c),.y(y));
    
    initial begin
        $dumpfile("tb_multiple_modules.vcd");
        $dumpvars(0,tb_multiple_modules);
        a=1'b0; b=1'b0; c=1'b0;
        #300 $finish;
    end
    
    always #75 a = ~a;
    always #10 b = ~b;
    always #55 c = ~c;
endmodule

WEEK1/Day-1/verilog_files/tb_multiple_modules.vcd
$date
	Sat Sep 27 22:55:55 2025
$end
$version
	Icarus Verilog
$end
$timescale
	1ps
$end
$scope module tb_multiple_modules $end
$var wire 1 ! y $end
$var reg 1 " a $end
$var reg 1 # b $end
$var reg 1 $ c $end
$scope module uut $end
$var wire 1 " a $end
$var wire 1 # b $end
$var wire 1 $ c $end
$var wire 1 ! y $end
$var wire 1 % net1 $end
$scope module u1 $end
$var wire 1 " a $end
$var wire 1 # b $end
$var wire 1 % y $end
$upscope $end
$scope module u2 $end
$var wire 1 % a $end
$var wire 1 $ b $end
$var wire 1 ! y $end
$upscope $end
$upscope $end
$upscope $end
$enddefinitions $end
$comment Show the parameter values. $end
$dumpall
$end
#0
$dumpvars
0%
0$
0#
0"
0!
$end
#10000
1#
#20000
0#
#30000
1#
#40000
0#
#50000
1#
#55000
1!
1$
#60000
0#
#70000
1#
#75000
1%
1"
#80000
0%
0#
#90000
1%
1#
#100000
0%
0#
#110000
1%
1!
1#
0$
#120000
0!
0%
0#
#130000
1!
1%
1#
#140000
0!
0%
0#
#150000
1#
0"
#160000
0#
#165000
1!
1$
#170000
1#
#180000
0#
#190000
1#
#200000
0#
#210000
1#
#220000
0!
0#
0$
#225000
1"
#230000
1!
1%
1#
#240000
0!
0%
0#
#250000
1!
1%
1#
#260000
0!
0%
0#
#270000
1!
1%
1#
#275000
1$
#280000
0%
0#
#290000
1%
1#
#300000
0%
0#
0"
